[
    {
        "addr": "臺南市安定區蘇厝1之31號",
        "dot_code": "A01",
        "dot_name": "前導車",
        "dot_Msg": "",
        "dot_ICO": "\/data\/E260102\/A02.png",
        "dot_Power": "12.2V",
        "gps_time8": "2026-01-06T09:16:31.000Z",
        "gps_time": "2026-01-06 09:16:31",
        "iconAnchor": "30,138",
        "pjName": "【行動政府-行動正能量】女力鐵馬精神",
        "gpsType": null,
        "WarnDot_Power": "08.0V",
        "GPS": [
            {
                "lat": 23.127917,
                "lng": 120.260033
            },
            {
                "lat": 23.128067,
                "lng": 120.260633
            },
            {
                "lat": 23.1283,
                "lng": 120.261417
            },
            {
                "lat": 23.128483,
                "lng": 120.262083
            },
            {
                "lat": 23.1287,
                "lng": 120.262833
            },
            {
                "lat": 23.128867,
                "lng": 120.263467
            },
            {
                "lat": 23.128917,
                "lng": 120.263567
            },
            {
                "lat": 23.128967,
                "lng": 120.26375
            },
            {
                "lat": 23.12915,
                "lng": 120.2644
            },
            {
                "lat": 23.1294,
                "lng": 120.265333
            }
        ]
    }
]