[
    {
        "addr": "臺南市新市區中興街146號",
        "dot_code": "A01",
        "dot_name": "前導車",
        "dot_Msg": "",
        "dot_ICO": "\/data\/E260102\/A02.png",
        "dot_Power": "12.3V",
        "gps_time8": "2026-01-06T10:34:50.000Z",
        "gps_time": "2026-01-06 10:34:50",
        "iconAnchor": "30,138",
        "pjName": "【行動政府-行動正能量】女力鐵馬精神",
        "gpsType": null,
        "WarnDot_Power": "08.0V",
        "GPS": [
            {
                "lat": 23.078117,
                "lng": 120.291683
            },
            {
                "lat": 23.078233,
                "lng": 120.291483
            },
            {
                "lat": 23.078233,
                "lng": 120.291483
            },
            {
                "lat": 23.07825,
                "lng": 120.29145
            },
            {
                "lat": 23.078267,
                "lng": 120.291433
            },
            {
                "lat": 23.078283,
                "lng": 120.291417
            },
            {
                "lat": 23.07835,
                "lng": 120.291267
            },
            {
                "lat": 23.078417,
                "lng": 120.291083
            },
            {
                "lat": 23.078467,
                "lng": 120.290933
            },
            {
                "lat": 23.078717,
                "lng": 120.290467
            }
        ]
    }
]