[
    {
        "addr": "臺南市新化區太平街25號",
        "dot_code": "A01",
        "dot_name": "前導車",
        "dot_Msg": "",
        "dot_ICO": "\/data\/E260102\/A02.png",
        "dot_Power": "12.1V",
        "gps_time8": "2026-01-06T12:56:50.000Z",
        "gps_time": "2026-01-06 12:56:50",
        "iconAnchor": "30,138",
        "pjName": "【行動政府-行動正能量】女力鐵馬精神",
        "gpsType": null,
        "WarnDot_Power": "08.0V",
        "GPS": [
            {
                "lat": 23.03965,
                "lng": 120.307083
            },
            {
                "lat": 23.03965,
                "lng": 120.307083
            },
            {
                "lat": 23.039633,
                "lng": 120.307083
            },
            {
                "lat": 23.039617,
                "lng": 120.3071
            },
            {
                "lat": 23.039617,
                "lng": 120.3071
            },
            {
                "lat": 23.039617,
                "lng": 120.3071
            },
            {
                "lat": 23.039617,
                "lng": 120.3071
            },
            {
                "lat": 23.039617,
                "lng": 120.3071
            },
            {
                "lat": 23.039617,
                "lng": 120.3071
            },
            {
                "lat": 23.039617,
                "lng": 120.307083
            }
        ]
    }
]