[
    {
        "addr": "臺南市安南區安昌街24號",
        "dot_code": "A01",
        "dot_name": "前導車",
        "dot_Msg": "",
        "dot_ICO": "\/data\/E260102\/A02.png",
        "dot_Power": "12.3V",
        "gps_time8": "2026-01-11T11:24:43.000Z",
        "gps_time": "2026-01-11 11:24:43",
        "iconAnchor": "30,138",
        "pjName": "【行動政府-行動正能量】女力鐵馬精神",
        "gpsType": null,
        "WarnDot_Power": "08.0V",
        "GPS": [
            {
                "lat": 23.067633,
                "lng": 120.217783
            },
            {
                "lat": 23.067633,
                "lng": 120.217783
            },
            {
                "lat": 23.067617,
                "lng": 120.217783
            },
            {
                "lat": 23.06765,
                "lng": 120.217783
            },
            {
                "lat": 23.067667,
                "lng": 120.21775
            },
            {
                "lat": 23.0679,
                "lng": 120.217767
            },
            {
                "lat": 23.0682,
                "lng": 120.218117
            },
            {
                "lat": 23.0681,
                "lng": 120.218533
            },
            {
                "lat": 23.068017,
                "lng": 120.219567
            },
            {
                "lat": 23.06805,
                "lng": 120.220467
            }
        ]
    }
]