[
    {
        "addr": "臺南市安南區國安街75號",
        "dot_code": "A01",
        "dot_name": "前導車",
        "dot_Msg": "",
        "dot_ICO": "\/data\/E260102\/A02.png",
        "dot_Power": "12.3V",
        "gps_time8": "2026-01-11T12:15:56.000Z",
        "gps_time": "2026-01-11 12:15:56",
        "iconAnchor": "30,138",
        "pjName": "【行動政府-行動正能量】女力鐵馬精神",
        "gpsType": null,
        "WarnDot_Power": "08.0V",
        "GPS": [
            {
                "lat": 23.0225,
                "lng": 120.189683
            },
            {
                "lat": 23.022417,
                "lng": 120.18915
            },
            {
                "lat": 23.022317,
                "lng": 120.1887
            },
            {
                "lat": 23.022233,
                "lng": 120.188217
            },
            {
                "lat": 23.02235,
                "lng": 120.1877
            },
            {
                "lat": 23.02265,
                "lng": 120.187633
            },
            {
                "lat": 23.022667,
                "lng": 120.187617
            },
            {
                "lat": 23.0228,
                "lng": 120.18755
            },
            {
                "lat": 23.023467,
                "lng": 120.1874
            },
            {
                "lat": 23.02425,
                "lng": 120.187233
            }
        ]
    }
]