[
    {
        "addr": "臺南市南化區北寮里北寮61-6號",
        "dot_code": "A01",
        "dot_name": "前導車",
        "dot_Msg": "",
        "dot_ICO": "\/data\/E260102\/A02.png",
        "dot_Power": "12.8V",
        "gps_time8": "2026-01-05T11:14:40.000Z",
        "gps_time": "2026-01-05 11:14:40",
        "iconAnchor": "30,138",
        "pjName": "【行動政府-行動正能量】女力鐵馬精神",
        "gpsType": null,
        "WarnDot_Power": "08.0V",
        "GPS": [
            {
                "lat": 23.0844,
                "lng": 120.4876
            },
            {
                "lat": 23.08525,
                "lng": 120.487317
            },
            {
                "lat": 23.085983,
                "lng": 120.487083
            },
            {
                "lat": 23.086783,
                "lng": 120.486833
            },
            {
                "lat": 23.08735,
                "lng": 120.486667
            },
            {
                "lat": 23.088233,
                "lng": 120.4866
            },
            {
                "lat": 23.0894,
                "lng": 120.486417
            },
            {
                "lat": 23.090617,
                "lng": 120.486117
            },
            {
                "lat": 23.091417,
                "lng": 120.485833
            },
            {
                "lat": 23.091967,
                "lng": 120.485433
            }
        ]
    }
]