[
    {
        "addr": "臺南市歸仁區中正北路一段384號",
        "dot_code": "A01",
        "dot_name": "前導車",
        "dot_Msg": "",
        "dot_ICO": "\/data\/E260102\/A02.png",
        "dot_Power": "12.1V",
        "gps_time8": "2026-01-08T13:41:33.000Z",
        "gps_time": "2026-01-08 13:41:33",
        "iconAnchor": "30,138",
        "pjName": "【行動政府-行動正能量】女力鐵馬精神",
        "gpsType": null,
        "WarnDot_Power": "08.0V",
        "GPS": [
            {
                "lat": 22.9772,
                "lng": 120.295083
            },
            {
                "lat": 22.976783,
                "lng": 120.295633
            },
            {
                "lat": 22.976767,
                "lng": 120.295867
            },
            {
                "lat": 22.976767,
                "lng": 120.295917
            },
            {
                "lat": 22.97665,
                "lng": 120.296317
            },
            {
                "lat": 22.976633,
                "lng": 120.296933
            },
            {
                "lat": 22.976517,
                "lng": 120.297783
            },
            {
                "lat": 22.976167,
                "lng": 120.29855
            },
            {
                "lat": 22.975683,
                "lng": 120.298567
            },
            {
                "lat": 22.975317,
                "lng": 120.298383
            }
        ]
    }
]