[
    {
        "addr": "臺南市將軍區",
        "dot_code": "A01",
        "dot_name": "前導車",
        "dot_Msg": "",
        "dot_ICO": "\/data\/E260102\/A02.png",
        "dot_Power": "12.3V",
        "gps_time8": "2026-01-10T13:48:41.000Z",
        "gps_time": "2026-01-10 13:48:41",
        "iconAnchor": "30,138",
        "pjName": "【行動政府-行動正能量】女力鐵馬精神",
        "gpsType": null,
        "WarnDot_Power": "08.0V",
        "GPS": [
            {
                "lat": 23.208633,
                "lng": 120.13165
            },
            {
                "lat": 23.2085,
                "lng": 120.1324
            },
            {
                "lat": 23.208067,
                "lng": 120.132633
            },
            {
                "lat": 23.207533,
                "lng": 120.1324
            },
            {
                "lat": 23.207033,
                "lng": 120.132633
            },
            {
                "lat": 23.206733,
                "lng": 120.132983
            },
            {
                "lat": 23.206283,
                "lng": 120.133467
            },
            {
                "lat": 23.20615,
                "lng": 120.13405
            },
            {
                "lat": 23.205883,
                "lng": 120.13405
            },
            {
                "lat": 23.205717,
                "lng": 120.13445
            }
        ]
    }
]