[
    {
        "addr": "臺南市將軍區.",
        "dot_code": "A01",
        "dot_name": "前導車",
        "dot_Msg": "",
        "dot_ICO": "\/data\/E260102\/A02.png",
        "dot_Power": "12.3V",
        "gps_time8": "2026-01-10T14:01:43.000Z",
        "gps_time": "2026-01-10 14:01:43",
        "iconAnchor": "30,138",
        "pjName": "【行動政府-行動正能量】女力鐵馬精神",
        "gpsType": null,
        "WarnDot_Power": "08.0V",
        "GPS": [
            {
                "lat": 23.218567,
                "lng": 120.110967
            },
            {
                "lat": 23.218617,
                "lng": 120.111617
            },
            {
                "lat": 23.218667,
                "lng": 120.11225
            },
            {
                "lat": 23.218717,
                "lng": 120.113
            },
            {
                "lat": 23.218783,
                "lng": 120.113767
            },
            {
                "lat": 23.218833,
                "lng": 120.114483
            },
            {
                "lat": 23.2189,
                "lng": 120.11515
            },
            {
                "lat": 23.219283,
                "lng": 120.11585
            },
            {
                "lat": 23.2195,
                "lng": 120.1162
            },
            {
                "lat": 23.219717,
                "lng": 120.116433
            }
        ]
    }
]