[
    {
        "addr": "臺南市佳里區頂部里頂部83-4號",
        "dot_code": "A01",
        "dot_name": "前導車",
        "dot_Msg": "",
        "dot_ICO": "\/data\/E260102\/A02.png",
        "dot_Power": "12.2V",
        "gps_time8": "2026-01-10T15:37:42.000Z",
        "gps_time": "2026-01-10 15:37:42",
        "iconAnchor": "30,138",
        "pjName": "【行動政府-行動正能量】女力鐵馬精神",
        "gpsType": null,
        "WarnDot_Power": "08.0V",
        "GPS": [
            {
                "lat": 23.1731,
                "lng": 120.150817
            },
            {
                "lat": 23.173117,
                "lng": 120.151367
            },
            {
                "lat": 23.173217,
                "lng": 120.151967
            },
            {
                "lat": 23.1735,
                "lng": 120.152583
            },
            {
                "lat": 23.1738,
                "lng": 120.153117
            },
            {
                "lat": 23.1743,
                "lng": 120.15305
            },
            {
                "lat": 23.174333,
                "lng": 120.15305
            },
            {
                "lat": 23.17435,
                "lng": 120.15305
            },
            {
                "lat": 23.174433,
                "lng": 120.15305
            },
            {
                "lat": 23.174883,
                "lng": 120.15295
            }
        ]
    }
]